GithugTongguanGonglve/README.md
GithugTongguanGonglve/__init__.py
GithugTongguanGonglve/__main__.py
GithugTongguanGonglve/file.epub
GithugTongguanGonglve/index.html
GithugTongguanGonglve/css/__init__.py
GithugTongguanGonglve/css/annotations.css
GithugTongguanGonglve/css/main.css
GithugTongguanGonglve/css/normalize.css
GithugTongguanGonglve/css/popup.css
GithugTongguanGonglve/font/__init__.py
GithugTongguanGonglve/font/fontello.eot
GithugTongguanGonglve/font/fontello.svg
GithugTongguanGonglve/font/fontello.ttf
GithugTongguanGonglve/font/fontello.woff
GithugTongguanGonglve/img/__init__.py
GithugTongguanGonglve/img/annotator-glyph-sprite.png
GithugTongguanGonglve/img/annotator-icon-sprite.png
GithugTongguanGonglve/img/apple-touch-icon.png
GithugTongguanGonglve/img/cancelfullscreen.png
GithugTongguanGonglve/img/close.png
GithugTongguanGonglve/img/fullscreen.png
GithugTongguanGonglve/img/loader.gif
GithugTongguanGonglve/img/menu-icon.png
GithugTongguanGonglve/img/save.png
GithugTongguanGonglve/img/saved.png
GithugTongguanGonglve/img/settings-s.png
GithugTongguanGonglve/img/settings.png
GithugTongguanGonglve/img/star.png
GithugTongguanGonglve/js/__init__.py
GithugTongguanGonglve/js/epub.js
GithugTongguanGonglve/js/epub.min.js
GithugTongguanGonglve/js/epub.min.map
GithugTongguanGonglve/js/hooks.min.js
GithugTongguanGonglve/js/hooks.min.map
GithugTongguanGonglve/js/reader.js
GithugTongguanGonglve/js/reader.js.map
GithugTongguanGonglve/js/reader.min.js
GithugTongguanGonglve/js/reader.min.map
GithugTongguanGonglve/js/hooks/__init__.py
GithugTongguanGonglve/js/hooks/extensions/__init__.py
GithugTongguanGonglve/js/hooks/extensions/highlight.js
GithugTongguanGonglve/js/libs/__init__.py
GithugTongguanGonglve/js/libs/jquery.min.js
GithugTongguanGonglve/js/libs/localforage.min.js
GithugTongguanGonglve/js/libs/screenfull.js
GithugTongguanGonglve/js/libs/screenfull.min.js
GithugTongguanGonglve/js/libs/zip.min.js
GithugTongguanGonglve/js/plugins/__init__.py
githug_tongguan_gonglve-2024.3.4.0.dist-info/METADATA
githug_tongguan_gonglve-2024.3.4.0.dist-info/WHEEL
githug_tongguan_gonglve-2024.3.4.0.dist-info/entry_points.txt
githug_tongguan_gonglve-2024.3.4.0.dist-info/top_level.txt
githug_tongguan_gonglve-2024.3.4.0.dist-info/RECORD
